st_searchbar/__init__.py
st_searchbar/frontend/build/asset-manifest.json
st_searchbar/frontend/build/bootstrap.min.css
st_searchbar/frontend/build/index.html
st_searchbar/frontend/build/precache-manifest.04c86ff0959d889800b3bdc51ad3d1a1.js
st_searchbar/frontend/build/precache-manifest.0e11f5be7ece44b52359d9e1ee04a7d5.js
st_searchbar/frontend/build/precache-manifest.650cf151427afe19129fd0661bf2a3c1.js
st_searchbar/frontend/build/precache-manifest.652fe121ae43334256596c31ca851f89.js
st_searchbar/frontend/build/precache-manifest.85ae4a4dffaadbea073bc09c720bbf24.js
st_searchbar/frontend/build/precache-manifest.8afcd2f8df502ba472f3e65eeee51615.js
st_searchbar/frontend/build/precache-manifest.c81079ac31c6a8533bc89850ea3aa800.js
st_searchbar/frontend/build/service-worker.js
st_searchbar/frontend/build/static/css/main.688d5a28.chunk.css
st_searchbar/frontend/build/static/css/main.688d5a28.chunk.css.map
st_searchbar/frontend/build/static/css/main.74c77d57.chunk.css
st_searchbar/frontend/build/static/css/main.74c77d57.chunk.css.map
st_searchbar/frontend/build/static/css/main.c9ab033c.chunk.css
st_searchbar/frontend/build/static/css/main.c9ab033c.chunk.css.map
st_searchbar/frontend/build/static/css/main.cb79e1e0.chunk.css
st_searchbar/frontend/build/static/css/main.cb79e1e0.chunk.css.map
st_searchbar/frontend/build/static/css/main.d8757a26.chunk.css
st_searchbar/frontend/build/static/css/main.d8757a26.chunk.css.map
st_searchbar/frontend/build/static/css/main.fda36f84.chunk.css
st_searchbar/frontend/build/static/css/main.fda36f84.chunk.css.map
st_searchbar/frontend/build/static/js/2.23099c93.chunk.js
st_searchbar/frontend/build/static/js/2.23099c93.chunk.js.LICENSE.txt
st_searchbar/frontend/build/static/js/2.23099c93.chunk.js.map
st_searchbar/frontend/build/static/js/2.522574df.chunk.js
st_searchbar/frontend/build/static/js/2.522574df.chunk.js.LICENSE.txt
st_searchbar/frontend/build/static/js/2.522574df.chunk.js.map
st_searchbar/frontend/build/static/js/main.554ed223.chunk.js
st_searchbar-0.0.9.dist-info/LICENSE
st_searchbar-0.0.9.dist-info/METADATA
st_searchbar-0.0.9.dist-info/WHEEL
st_searchbar-0.0.9.dist-info/top_level.txt
st_searchbar-0.0.9.dist-info/RECORD
