Metadata-Version: 2.1
Name: st-searchbar
Version: 0.0.9
Summary: A search bar component for streamlit with audio input and suggestions.
Home-page: 
Author: Asvin Ragunathan
Author-email: r.asvin@hotmail.com
License: UNKNOWN
Platform: UNKNOWN
Requires-Python: >=3.6
License-File: LICENSE
Requires-Dist: streamlit (>=0.63)
